syndata/__init__.py
syndata/centers.py
syndata/core.py
syndata/distributions.py
syndata/maxmin.py
syndata/validation.py
syndata-0.1.1.dist-info/LICENSE
syndata-0.1.1.dist-info/METADATA
syndata-0.1.1.dist-info/WHEEL
syndata-0.1.1.dist-info/top_level.txt
syndata-0.1.1.dist-info/RECORD
