Metadata-Version: 2.1
Name: syndata
Version: 0.1.1
Summary: Generate synthetic data with clusters.
Home-page: https://github.com/mzelling/syndata
Author: Michael Zellinger
Author-email: michael.zellinger@stat.math.ethz.ch
License: UNKNOWN
Project-URL: Bug Tracker, https://github.com/mzelling/syndata/issues
Platform: UNKNOWN
Classifier: Programming Language :: Python :: 3
Classifier: License :: OSI Approved :: MIT License
Classifier: Operating System :: OS Independent
Requires-Python: >=3.6
License-File: LICENSE
